nxpy_file_object-1.0.0-py3.7-nspkg.pth
nxpy/core/file_object/__init__.py
nxpy/core/file_object/file_object.py
nxpy_file_object-1.0.0.dist-info/LICENSE.txt
nxpy_file_object-1.0.0.dist-info/METADATA
nxpy_file_object-1.0.0.dist-info/WHEEL
nxpy_file_object-1.0.0.dist-info/namespace_packages.txt
nxpy_file_object-1.0.0.dist-info/top_level.txt
nxpy_file_object-1.0.0.dist-info/RECORD
