Metadata-Version: 2.1
Name: nxpy-file-object
Version: 1.0.0
Summary: Helper classes to implement file-like objects
Home-page: UNKNOWN
Author: Nicola Musatti
Author-email: nicola.musatti@gmail.com
License: Boost Software License 1.0 (BSL-1.0)
Project-URL: Documentation, https://nxpy.readthedocs.io/en/latest/
Project-URL: Source Code, https://github.com/nmusatti/nxpy
Platform: UNKNOWN
Classifier: Development Status :: 5 - Production/Stable
Classifier: Intended Audience :: Developers
Classifier: License :: OSI Approved :: Boost Software License 1.0 (BSL-1.0)
Classifier: Programming Language :: Python :: 2
Classifier: Programming Language :: Python :: 2.7
Classifier: Programming Language :: Python :: 3
Classifier: Programming Language :: Python :: 3.4
Classifier: Programming Language :: Python :: 3.5
Classifier: Programming Language :: Python :: 3.6
Classifier: Programming Language :: Python :: 3.7
Classifier: Topic :: Software Development :: Libraries
